matbi/01_VerilogHDL/chapter_20/dongwon_cache.v
//Description: Direct mapped cache

module dongwon_cache
//param
#(
    parameter ADDR_WIDTH = 32,
    parameter DATA_WIDTH = 32,          //2^5
    parameter CACHE_SIZE = 4096,        //2^12
    parameter CACHE_MODE = "DIRECT MAPPED"
)
(
    input clk,
    input reset_n,
    input [ADDR_WIDTH-1:0] addr,
    input we,
    input run,
    input [DATA_WIDTH-1:0] in_data,
    output reg [DATA_WIDTH-1:0] out_data,
    output reg [2:0] state_of_cache
);

localparam SIZE_OF_BYTE_OFFSET = $clog2(DATA_WIDTH/8);
localparam SIZE_OF_INDEX = $clog2(CACHE_SIZE) - SIZE_OF_BYTE_OFFSET;
localparam SIZE_OF_VALID = 1;
localparam SIZE_OF_TAG = (ADDR_WIDTH)-(SIZE_OF_INDEX)-(SIZE_OF_BYTE_OFFSET);
localparam SIZE_OF_CACHE_LINE = (SIZE_OF_VALID)+(SIZE_OF_TAG)+(DATA_WIDTH);
localparam IDX_VALID = SIZE_OF_CACHE_LINE - 1; 

//Cache
reg [SIZE_OF_CACHE_LINE-1:0] cache_line[0:SIZE_OF_INDEX-1];

wire [SIZE_OF_BYTE_OFFSET-1:0] byte_offset;
wire [SIZE_OF_INDEX-1:0] index; 
wire [SIZE_OF_TAG-1:0] tag;

//Parsing address -> tag/index/byte offset
assign byte_offset = addr[SIZE_OF_BYTE_OFFSET-1 : 0];
assign index = addr[SIZE_OF_INDEX-1 : SIZE_OF_BYTE_OFFSET];
assign tag = addr[SIZE_OF_TAG-1 : SIZE_OF_INDEX+SIZE_OF_BYTE_OFFSET];


//Cache initialization
integer iter=0;
always @(posedge clk or negedge reset_n) begin
    if(!reset_n)begin
        for(iter=0; iter < CACHE_SIZE-1; iter=iter+1) begin
            cache_line[iter] <= {DATA_WIDTH{1'b0}};
        end       
    end
end

//update state of cache {Read|Write, Hit|Miss}
localparam CACHE_WRITE        = 3'b010;
localparam CACHE_READ_MISS    = 3'b100;
localparam CACHE_READ_HIT     = 3'b101;
localparam CACHE_IDLE         = 3'b000;

//localparam CACHE_WRITE_MISS   = 2'b10;
//localparam CACHE_WRITE_HIT    = 2'b11;

wire [3:0] abc;
assign abc = in_data & 32'hffff_ffff;

//Update Read & Write
always @(posedge clk) begin
    state_of_cache = CACHE_IDLE;
    if((CACHE_MODE == "DIRECT MAPPED") && run) begin
        if(we) begin                                            
                if(cache_line[index][IDX_VALID] == 0) begin  
                    state_of_cache <= CACHE_WRITE;
                    cache_line[index][DATA_WIDTH-1:0] <= in_data;
                    cache_line[index][IDX_VALID] <= 1'b1;
                end else                          
                    state_of_cache <= CACHE_WRITE;              
                    cache_line[index][DATA_WIDTH-1] <=  in_data;
                end
        else begin                                              
                if(cache_line[index][IDX_VALID] == 0) begin 
                    state_of_cache <= CACHE_READ_MISS;    
                    cache_line[index][DATA_WIDTH-1:0] <= in_data; //from RAM
                    cache_line[index][IDX_VALID] <= 1'b1;
                end else begin                                  
                    state_of_cache <= CACHE_READ_HIT;
                    out_data <= cache_line[index] & 32'hffff_ffff;
                    cache_line[index][IDX_VALID] <= 1'b1;
                end                                     
            end                 
        end
end  

endmodule

matbi/01_VerilogHDL/chapter_20/dongwon_ram.v
`timescale 1 ns/ 1 ps
module dongwon_ram
#(
    parameter ADDR_WIDTH = 8,
    parameter DATA_WIDTH = 8,
    parameter MEM_SIZE = 4096
)
(
    input clk,
    input reset_n,
    input [ADDR_WIDTH-1:0] addr,
    input [DATA_WIDTH-1:0] in_data,
    input run,
    input we,
    input [2:0] state_of_cache,
    output reg [DATA_WIDTH-1:0] out_data = 8'b0000_0000
);

localparam CACHE_WRITE        = 3'b010;
localparam CACHE_READ_MISS    = 3'b100;
localparam CACHE_READ_HIT     = 3'b101;
localparam CACHE_IDLE         = 3'b000;



//(* ram_style = "block" *)reg [DATA_WIDTH-1:0] ram[0:MEM_SIZE-1];
//reg [DATA_WIDTH-1:0] ram[0:MEM_SIZE-1];

reg [8-1:0] ram[0:MEM_SIZE-1];
integer iter=0;
always @(posedge clk or negedge reset_n) begin
    if(!reset_n)begin
        for(iter=0; iter<MEM_SIZE-1; iter=iter+1)begin
            ram[iter] <= {DATA_WIDTH{1'b0}};
        end
    end
end

// read & write
always @(posedge clk) begin
    if(run) begin
        if (we) begin
            ram[addr] <= (in_data)&(8'hff);
            ram[addr+1] <= (in_data>>8)&(8'hff);
            ram[addr+2] <= (in_data>>16)&(8'hff);
            ram[addr+3] <= (in_data>>24)&(8'hff);    
        end
            
        else if(~we)begin
            out_data <= (ram[addr+0]&(8'hff)<<0)
                        |(ram[addr+1]&(8'hff)<<8)
                        |(ram[addr+2]&(8'hff)<<16)
                        |(ram[addr+3]&(8'hff)<<24);        
        end
    end    
end

endmodule

matbi/01_VerilogHDL/chapter_20/tb_dongwon_ram.v
`timescale 1 ns/ 1 ps

`define ADDR_WIDTH 32
`define DATA_WIDTH 32
`define MEM_SIZE 1024
`define CACHE_SIZE 64
`define CACHE_MODE "DIRECT MAPPED"

module tb_dongwon_ram ();

//Program cnter
//wire [`ADDR_WIDTH-1:0] pc;
reg pc_restart;
reg [`ADDR_WIDTH-1:0] pc;
//Memory
reg r_we;
reg c_we;
reg clk;
reg reset_n;
reg r_run;
reg c_run;

reg [`DATA_WIDTH-1:0] r_in_data;
reg [`DATA_WIDTH-1:0] c_in_data;
wire [`DATA_WIDTH-1:0] r_out_data;
wire [`DATA_WIDTH-1:0] c_out_data;
reg [`DATA_WIDTH-1:0] t_out_data;
wire [2:0] state_of_cache;

//local praram
localparam CACHE_WRITE        = 3'b010;
localparam CACHE_READ_MISS    = 3'b100;
localparam CACHE_READ_HIT     = 3'b101;
localparam CACHE_IDLE         = 3'b000;

integer iter = 0;
integer count = 1;
//clock generation
always
    #5 clk = ~clk;

initial begin
    $dumpfile("output.vcd");
    $dumpvars(0, tb_dongwon_ram);

    //initialization
    reset_n = 1;
    pc_restart = 1;
    clk = 1; 
    
    r_run = 1;
    r_we = 0;
    c_run = 0;
    c_we = 0;
    
    c_in_data = 0;
    r_in_data = 0;

    //1. RAM initialization (OK) 
    begin
        #10
        reset_n <= 0 ;     
        r_we <= 1; 
        r_run <=1;
        pc = 0;

        #10
        reset_n = 1;
        for (iter=0; iter<32; iter=iter+1) begin
            r_in_data <= iter;
            pc <= pc+4;
            #10;
        end
    end
    
    // 2. Cache read(Cache miss) 
    begin
        pc_restart <= 0;
        r_run <=1;
        c_run <=1;
        r_we <= 0; 
        c_we <= 0;
        pc = 0;

        #10
        pc_restart <= 1;
        for (iter=0; iter<32; iter=iter+1) begin
                c_in_data <= r_out_data;
                pc = pc+4;
                #10;
        end
    end
    

    // 3. Cache read(Cache hit)
    begin
        #10
        c_we <= 0;
        r_run <=0;
        c_run <=1;
        pc_restart <= 0;
        pc = 0;

        #10
        pc_restart <= 1;
        for (iter=0; iter<32; iter=iter+1) begin     
            if(state_of_cache == CACHE_READ_HIT)
                t_out_data <= c_out_data;
                pc <= pc+4;
                #10;
        end
    end
    

    $finish;
end


// Memory
dongwon_ram 
#(  
    .ADDR_WIDTH             (`ADDR_WIDTH),
    .DATA_WIDTH             (`DATA_WIDTH),
    .MEM_SIZE               (`MEM_SIZE)
)
u_dongwon_ram (
    .clk                    (clk),
    .reset_n                (reset_n),
    .addr                   (pc),
    .run                    (r_run),
    .in_data                (r_in_data),
    .we                     (r_we),
    .out_data               (r_out_data),
    .state_of_cache         (state_of_cache)
);


//cpu
// dongwon_cpu
// #(
//     .ADDR_WIDTH             (`ADDR_WIDTH)
// )
// u_dongwon_cpu
// (
//     .reset_n                (reset_n),
//     .clk                    (clk),
//     .pc                     (pc),
//     .restart_n              (pc_restart)
// );

//cache
dongwon_cache
#(
    .ADDR_WIDTH             (`ADDR_WIDTH),
    .DATA_WIDTH             (`DATA_WIDTH),
    .CACHE_SIZE             (`CACHE_SIZE),
    .CACHE_MODE             (`CACHE_MODE)
)       
u_dongwon_cache(        
    .clk                    (clk),
    .reset_n                (reset_n),
    .we                     (c_we),
    .addr                   (pc),
    .run                    (c_run),
    .out_data               (c_out_data),
    .in_data                (c_in_data),
    .state_of_cache         (state_of_cache)
);
    
endmodule

matbi/01_VerilogHDL/chapter_20/dongwon_ram/dongwon_ram.sim/sim_1/behav/xsim/output.vcd
$date
   Tue Feb 23 16:17:46 2021
$end
$version
  2019.2
$end
$timescale
  1ps
$end
$scope module tb_dongwon_ram $end
$var reg 1 ! pc_restart $end
$var reg 32 " pc [31:0] $end
$var reg 1 # r_we $end
$var reg 1 $ c_we $end
$var reg 1 % clk $end
$var reg 1 & reset_n $end
$var reg 1 ' r_run $end
$var reg 1 ( c_run $end
$var reg 32 ) r_in_data [31:0] $end
$var reg 32 * c_in_data [31:0] $end
$var wire 32 + r_out_data [31:0] $end
$var wire 32 , c_out_data [31:0] $end
$var reg 32 - t_out_data [31:0] $end
$var wire 3 . state_of_cache [2:0] $end
$var integer 32 / iter $end
$var integer 32 0 count $end
$var parameter 3 1 CACHE_WRITE [2:0] $end
$var parameter 3 2 CACHE_READ_MISS [2:0] $end
$var parameter 3 3 CACHE_READ_HIT [2:0] $end
$var parameter 3 4 CACHE_IDLE [2:0] $end
$scope module u_dongwon_ram $end
$var wire 1 5 clk $end
$var wire 1 6 reset_n $end
$var wire 32 7 addr [31:0] $end
$var wire 32 8 in_data [31:0] $end
$var wire 1 9 run $end
$var wire 1 : we $end
$var wire 3 . state_of_cache [2:0] $end
$var reg 32 ; out_data [31:0] $end
$var integer 32 < iter $end
$var parameter 32 = ADDR_WIDTH [31:0] $end
$var parameter 32 > DATA_WIDTH [31:0] $end
$var parameter 32 ? MEM_SIZE [31:0] $end
$var parameter 3 @ CACHE_WRITE [2:0] $end
$var parameter 3 A CACHE_READ_MISS [2:0] $end
$var parameter 3 B CACHE_READ_HIT [2:0] $end
$var parameter 3 C CACHE_IDLE [2:0] $end
$upscope $end
$scope module u_dongwon_cache $end
$var wire 1 D clk $end
$var wire 1 E reset_n $end
$var wire 32 F addr [31:0] $end
$var wire 1 G we $end
$var wire 1 H run $end
$var wire 32 I in_data [31:0] $end
$var reg 32 J out_data [31:0] $end
$var reg 3 K state_of_cache [2:0] $end
$var wire 2 L byte_offset [1:0] $end
$var wire 4 M index [3:0] $end
$var wire 26 N tag [25:0] $end
$var integer 32 O iter $end
$var wire 4 P abc [3:0] $end
$var parameter 32 Q ADDR_WIDTH [31:0] $end
$var parameter 32 R DATA_WIDTH [31:0] $end
$var parameter 32 S CACHE_SIZE [31:0] $end
$var parameter 104 T CACHE_MODE [103:0] $end
$var parameter 32 U SIZE_OF_BYTE_OFFSET [31:0] $end
$var parameter 32 V SIZE_OF_INDEX [31:0] $end
$var parameter 32 W SIZE_OF_VALID [31:0] $end
$var parameter 32 X SIZE_OF_TAG [31:0] $end
$var parameter 32 Y SIZE_OF_CACHE_LINE [31:0] $end
$var parameter 32 Z IDX_VALID [31:0] $end
$var parameter 3 [ CACHE_WRITE [2:0] $end
$var parameter 3 \ CACHE_READ_MISS [2:0] $end
$var parameter 3 ] CACHE_READ_HIT [2:0] $end
$var parameter 3 ^ CACHE_IDLE [2:0] $end
$upscope $end
$upscope $end
$enddefinitions $end
#0
$dumpvars
1!
bx "
0#
0$
1%
1&
1'
0(
b0 )
b0 *
b0xxxxxxxx +
bx ,
bx -
b0 .
b0 /
b1 0
b10 1
b100 2
b101 3
b0 4
15
16
bx 7
b0 8
19
0:
b0xxxxxxxx ;
b0 <
b100000 =
b100000 >
b10000000000 ?
b10 @
b100 A
b101 B
b0 C
1D
1E
bx F
0G
0H
b0 I
bx J
b0 K
bx L
b0xx M
b0xxxxxxxxxxxxxxxxxxxx N
b0 O
b0 P
b100000 Q
b100000 R
b1000000 S
b1000100010010010101001001000101010000110101010000100000010011010100000101010000010100000100010101000100 T
b10 U
b100 V
b1 W
b11010 X
b111011 Y
b111010 Z
b10 [
b100 \
b101 ]
b0 ^
$end
#5000
0%
05
0D
#10000
b0 "
1#
1%
0&
15
06
b0 7
1:
b0xxxxxxxx ;
b1111111111 <
1D
0E
b0 F
b0 K
b0 L
b0 M
b0 N
b111111 O
#15000
0%
05
0D
#20000
b100 "
1%
1&
b0 )
15
16
b100 7
1D
1E
b100 F
b0 K
b1 M
#25000
0%
05
0D
#30000
b1000 "
1%
b1 )
b1 /
15
b1000 7
b1 8
1D
b1000 F
b0 K
b10 M
#35000
0%
05
0D
#40000
b1100 "
1%
b10 )
b10 /
15
b1100 7
b10 8
1D
b1100 F
b0 K
b11 M
#45000
0%
05
0D
#50000
b10000 "
1%
b11 )
b11 /
15
b10000 7
b11 8
1D
b10000 F
b0 K
b0 M
#55000
0%
05
0D
#60000
b10100 "
1%
b100 )
b100 /
15
b10100 7
b100 8
1D
b10100 F
b0 K
b1 M
#65000
0%
05
0D
#70000
b11000 "
1%
b101 )
b101 /
15
b11000 7
b101 8
1D
b11000 F
b0 K
b10 M
#75000
0%
05
0D
#80000
b11100 "
1%
b110 )
b110 /
15
b11100 7
b110 8
1D
b11100 F
b0 K
b11 M
#85000
0%
05
0D
#90000
b100000 "
1%
b111 )
b111 /
15
b100000 7
b111 8
1D
b100000 F
b0 K
b0 M
#95000
0%
05
0D
#100000
b100100 "
1%
b1000 )
b1000 /
15
b100100 7
b1000 8
1D
b100100 F
b0 K
b1 M
#105000
0%
05
0D
#110000
b101000 "
1%
b1001 )
b1001 /
15
b101000 7
b1001 8
1D
b101000 F
b0 K
b10 M
#115000
0%
05
0D
#120000
b101100 "
1%
b1010 )
b1010 /
15
b101100 7
b1010 8
1D
b101100 F
b0 K
b11 M
#125000
0%
05
0D
#130000
b110000 "
1%
b1011 )
b1011 /
15
b110000 7
b1011 8
1D
b110000 F
b0 K
b0 M
#135000
0%
05
0D
#140000
b110100 "
1%
b1100 )
b1100 /
15
b110100 7
b1100 8
1D
b110100 F
b0 K
b1 M
#145000
0%
05
0D
#150000
b111000 "
1%
b1101 )
b1101 /
15
b111000 7
b1101 8
1D
b111000 F
b0 K
b10 M
#155000
0%
05
0D
#160000
b111100 "
1%
b1110 )
b1110 /
15
b111100 7
b1110 8
1D
b111100 F
b0 K
b11 M
#165000
0%
05
0D
#170000
b1000000 "
1%
b1111 )
b1111 /
15
b1000000 7
b1111 8
1D
b1000000 F
b0 K
b0 M
b1 N
#175000
0%
05
0D
#180000
b1000100 "
1%
b10000 )
b10000 /
15
b1000100 7
b10000 8
1D
b1000100 F
b0 K
b1 M
#185000
0%
05
0D
#190000
b1001000 "
1%
b10001 )
b10001 /
15
b1001000 7
b10001 8
1D
b1001000 F
b0 K
b10 M
#195000
0%
05
0D
#200000
b1001100 "
1%
b10010 )
b10010 /
15
b1001100 7
b10010 8
1D
b1001100 F
b0 K
b11 M
#205000
0%
05
0D
#210000
b1010000 "
1%
b10011 )
b10011 /
15
b1010000 7
b10011 8
1D
b1010000 F
b0 K
b0 M
#215000
0%
05
0D
#220000
b1010100 "
1%
b10100 )
b10100 /
15
b1010100 7
b10100 8
1D
b1010100 F
b0 K
b1 M
#225000
0%
05
0D
#230000
b1011000 "
1%
b10101 )
b10101 /
15
b1011000 7
b10101 8
1D
b1011000 F
b0 K
b10 M
#235000
0%
05
0D
#240000
b1011100 "
1%
b10110 )
b10110 /
15
b1011100 7
b10110 8
1D
b1011100 F
b0 K
b11 M
#245000
0%
05
0D
#250000
b1100000 "
1%
b10111 )
b10111 /
15
b1100000 7
b10111 8
1D
b1100000 F
b0 K
b0 M
#255000
0%
05
0D
#260000
b1100100 "
1%
b11000 )
b11000 /
15
b1100100 7
b11000 8
1D
b1100100 F
b0 K
b1 M
#265000
0%
05
0D
#270000
b1101000 "
1%
b11001 )
b11001 /
15
b1101000 7
b11001 8
1D
b1101000 F
b0 K
b10 M
#275000
0%
05
0D
#280000
b1101100 "
1%
b11010 )
b11010 /
15
b1101100 7
b11010 8
1D
b1101100 F
b0 K
b11 M
#285000
0%
05
0D
#290000
b1110000 "
1%
b11011 )
b11011 /
15
b1110000 7
b11011 8
1D
b1110000 F
b0 K
b0 M
#295000
0%
05
0D
#300000
b1110100 "
1%
b11100 )
b11100 /
15
b1110100 7
b11100 8
1D
b1110100 F
b0 K
b1 M
#305000
0%
05
0D
#310000
b1111000 "
1%
b11101 )
b11101 /
15
b1111000 7
b11101 8
1D
b1111000 F
b0 K
b10 M
#315000
0%
05
0D
#320000
b1111100 "
1%
b11110 )
b11110 /
15
b1111100 7
b11110 8
1D
b1111100 F
b0 K
b11 M
#325000
0%
05
0D
#330000
b10000000 "
1%
b11111 )
b11111 /
15
b10000000 7
b11111 8
1D
b10000000 F
b0 K
b0 M
b10 N
#335000
0%
05
0D
#340000
0!
b0 "
0#
1%
1(
b100000 /
15
b0 7
0:
1D
b0 F
1H
b0 K
b0 N
#345000
0%
05
0D
#350000
1!
b100 "
1%
b0xxxxxxxx *
b0 +
b100 .
b0 /
15
b100 7
b0 ;
1D
b100 F
b0xxxxxxxx I
b100 K
b1 M
bx P
#355000
0%
05
0D
#360000
b1000 "
1%
b0 *
b1 +
b100 .
b1 /
15
b1000 7
b1 ;
1D
b1000 F
b0 I
b100 K
b10 M
b0 P
#365000
0%
05
0D
#370000
b1100 "
1%
b1 *
b10 +
b100 .
b10 /
15
b1100 7
b10 ;
1D
b1100 F
b1 I
b100 K
b11 M
b1 P
#375000
0%
05
0D
#380000
b10000 "
1%
b10 *
b11 +
b100 .
b11 /
15
b10000 7
b11 ;
1D
b10000 F
b10 I
b100 K
b0 M
b10 P
#385000
0%
05
0D
#390000
b10100 "
1%
b11 *
b100 +
b0 ,
b101 .
b100 /
15
b10100 7
b100 ;
1D
b10100 F
b11 I
b0 J
b101 K
b1 M
b11 P
#395000
0%
05
0D
#400000
b11000 "
1%
b100 *
b101 +
b0xxxxxxxx ,
b101 .
b101 /
15
b11000 7
b101 ;
1D
b11000 F
b100 I
b0xxxxxxxx J
b101 K
b10 M
b100 P
#405000
0%
05
0D
#410000
b11100 "
1%
b101 *
b110 +
b0 ,
b101 .
b110 /
15
b11100 7
b110 ;
1D
b11100 F
b101 I
b0 J
b101 K
b11 M
b101 P
#415000
0%
05
0D
#420000
b100000 "
1%
b110 *
b111 +
b1 ,
b101 .
b111 /
15
b100000 7
b111 ;
1D
b100000 F
b110 I
b1 J
b101 K
b0 M
b110 P
#425000
0%
05
0D
#430000
b100100 "
1%
b111 *
b1000 +
b0 ,
b101 .
b1000 /
15
b100100 7
b1000 ;
1D
b100100 F
b111 I
b0 J
b101 K
b1 M
b111 P
#435000
0%
05
0D
#440000
b101000 "
1%
b1000 *
b1001 +
b0xxxxxxxx ,
b101 .
b1001 /
15
b101000 7
b1001 ;
1D
b101000 F
b1000 I
b0xxxxxxxx J
b101 K
b10 M
b1000 P
#445000
0%
05
0D
#450000
b101100 "
1%
b1001 *
b1010 +
b0 ,
b101 .
b1010 /
15
b101100 7
b1010 ;
1D
b101100 F
b1001 I
b0 J
b101 K
b11 M
b1001 P
#455000
0%
05
0D
#460000
b110000 "
1%
b1010 *
b1011 +
b1 ,
b101 .
b1011 /
15
b110000 7
b1011 ;
1D
b110000 F
b1010 I
b1 J
b101 K
b0 M
b1010 P
#465000
0%
05
0D
#470000
b110100 "
1%
b1011 *
b1100 +
b0 ,
b101 .
b1100 /
15
b110100 7
b1100 ;
1D
b110100 F
b1011 I
b0 J
b101 K
b1 M
b1011 P
#475000
0%
05
0D
#480000
b111000 "
1%
b1100 *
b1101 +
b0xxxxxxxx ,
b101 .
b1101 /
15
b111000 7
b1101 ;
1D
b111000 F
b1100 I
b0xxxxxxxx J
b101 K
b10 M
b1100 P
#485000
0%
05
0D
#490000
b111100 "
1%
b1101 *
b1110 +
b0 ,
b101 .
b1110 /
15
b111100 7
b1110 ;
1D
b111100 F
b1101 I
b0 J
b101 K
b11 M
b1101 P
#495000
0%
05
0D
#500000
b1000000 "
1%
b1110 *
b1111 +
b1 ,
b101 .
b1111 /
15
b1000000 7
b1111 ;
1D
b1000000 F
b1110 I
b1 J
b101 K
b0 M
b1 N
b1110 P
#505000
0%
05
0D
#510000
b1000100 "
1%
b1111 *
b10000 +
b0 ,
b101 .
b10000 /
15
b1000100 7
b10000 ;
1D
b1000100 F
b1111 I
b0 J
b101 K
b1 M
b1111 P
#515000
0%
05
0D
#520000
b1001000 "
1%
b10000 *
b10001 +
b0xxxxxxxx ,
b101 .
b10001 /
15
b1001000 7
b10001 ;
1D
b1001000 F
b10000 I
b0xxxxxxxx J
b101 K
b10 M
b0 P
#525000
0%
05
0D
#530000
b1001100 "
1%
b10001 *
b10010 +
b0 ,
b101 .
b10010 /
15
b1001100 7
b10010 ;
1D
b1001100 F
b10001 I
b0 J
b101 K
b11 M
b1 P
#535000
0%
05
0D
#540000
b1010000 "
1%
b10010 *
b10011 +
b1 ,
b101 .
b10011 /
15
b1010000 7
b10011 ;
1D
b1010000 F
b10010 I
b1 J
b101 K
b0 M
b10 P
#545000
0%
05
0D
#550000
b1010100 "
1%
b10011 *
b10100 +
b0 ,
b101 .
b10100 /
15
b1010100 7
b10100 ;
1D
b1010100 F
b10011 I
b0 J
b101 K
b1 M
b11 P
#555000
0%
05
0D
#560000
b1011000 "
1%
b10100 *
b10101 +
b0xxxxxxxx ,
b101 .
b10101 /
15
b1011000 7
b10101 ;
1D
b1011000 F
b10100 I
b0xxxxxxxx J
b101 K
b10 M
b100 P
#565000
0%
05
0D
#570000
b1011100 "
1%
b10101 *
b10110 +
b0 ,
b101 .
b10110 /
15
b1011100 7
b10110 ;
1D
b1011100 F
b10101 I
b0 J
b101 K
b11 M
b101 P
#575000
0%
05
0D
#580000
b1100000 "
1%
b10110 *
b10111 +
b1 ,
b101 .
b10111 /
15
b1100000 7
b10111 ;
1D
b1100000 F
b10110 I
b1 J
b101 K
b0 M
b110 P
#585000
0%
05
0D
#590000
b1100100 "
1%
b10111 *
b11000 +
b0 ,
b101 .
b11000 /
15
b1100100 7
b11000 ;
1D
b1100100 F
b10111 I
b0 J
b101 K
b1 M
b111 P
#595000
0%
05
0D
#600000
b1101000 "
1%
b11000 *
b11001 +
b0xxxxxxxx ,
b101 .
b11001 /
15
b1101000 7
b11001 ;
1D
b1101000 F
b11000 I
b0xxxxxxxx J
b101 K
b10 M
b1000 P
#605000
0%
05
0D
#610000
b1101100 "
1%
b11001 *
b11010 +
b0 ,
b101 .
b11010 /
15
b1101100 7
b11010 ;
1D
b1101100 F
b11001 I
b0 J
b101 K
b11 M
b1001 P
#615000
0%
05
0D
#620000
b1110000 "
1%
b11010 *
b11011 +
b1 ,
b101 .
b11011 /
15
b1110000 7
b11011 ;
1D
b1110000 F
b11010 I
b1 J
b101 K
b0 M
b1010 P
#625000
0%
05
0D
#630000
b1110100 "
1%
b11011 *
b11100 +
b0 ,
b101 .
b11100 /
15
b1110100 7
b11100 ;
1D
b1110100 F
b11011 I
b0 J
b101 K
b1 M
b1011 P
#635000
0%
05
0D
#640000
b1111000 "
1%
b11100 *
b11101 +
b0xxxxxxxx ,
b101 .
b11101 /
15
b1111000 7
b11101 ;
1D
b1111000 F
b11100 I
b0xxxxxxxx J
b101 K
b10 M
b1100 P
#645000
0%
05
0D
#650000
b1111100 "
1%
b11101 *
b11110 +
b0 ,
b101 .
b11110 /
15
b1111100 7
b11110 ;
1D
b1111100 F
b11101 I
b0 J
b101 K
b11 M
b1101 P
#655000
0%
05
0D
#660000
b10000000 "
1%
b11110 *
b0 +
b1 ,
b101 .
b11111 /
15
b10000000 7
b0 ;
1D
b10000000 F
b11110 I
b1 J
b101 K
b0 M
b10 N
b1110 P
#665000
0%
05
0D
#670000
1%
b101 .
b100000 /
15
b0 ;
1D
b101 K
#675000
0%
05
0D
#680000
0!
b0 "
1%
0'
b11111 +
b101 .
15
b0 7
09
b11111 ;
1D
b0 F
b101 K
b0 N
#685000
0%
05
0D
#690000
1!
b100 "
1%
b1 -
b101 .
b0 /
15
b100 7
1D
b100 F
b101 K
b1 M
#695000
0%
05
0D
#700000
b1000 "
1%
b0 ,
b101 .
b1 /
15
b1000 7
1D
b1000 F
b0 J
b101 K
b10 M
#705000
0%
05
0D
#710000
b1100 "
1%
b0xxxxxxxx ,
b0 -
b101 .
b10 /
15
b1100 7
1D
b1100 F
b0xxxxxxxx J
b101 K
b11 M
#715000
0%
05
0D
#720000
b10000 "
1%
b0 ,
b0xxxxxxxx -
b101 .
b11 /
15
b10000 7
1D
b10000 F
b0 J
b101 K
b0 M
#725000
0%
05
0D
#730000
b10100 "
1%
b1 ,
b0 -
b101 .
b100 /
15
b10100 7
1D
b10100 F
b1 J
b101 K
b1 M
#735000
0%
05
0D
#740000
b11000 "
1%
b0 ,
b1 -
b101 .
b101 /
15
b11000 7
1D
b11000 F
b0 J
b101 K
b10 M
#745000
0%
05
0D
#750000
b11100 "
1%
b0xxxxxxxx ,
b0 -
b101 .
b110 /
15
b11100 7
1D
b11100 F
b0xxxxxxxx J
b101 K
b11 M
#755000
0%
05
0D
#760000
b100000 "
1%
b0 ,
b0xxxxxxxx -
b101 .
b111 /
15
b100000 7
1D
b100000 F
b0 J
b101 K
b0 M
#765000
0%
05
0D
#770000
b100100 "
1%
b1 ,
b0 -
b101 .
b1000 /
15
b100100 7
1D
b100100 F
b1 J
b101 K
b1 M
#775000
0%
05
0D
#780000
b101000 "
1%
b0 ,
b1 -
b101 .
b1001 /
15
b101000 7
1D
b101000 F
b0 J
b101 K
b10 M
#785000
0%
05
0D
#790000
b101100 "
1%
b0xxxxxxxx ,
b0 -
b101 .
b1010 /
15
b101100 7
1D
b101100 F
b0xxxxxxxx J
b101 K
b11 M
#795000
0%
05
0D
#800000
b110000 "
1%
b0 ,
b0xxxxxxxx -
b101 .
b1011 /
15
b110000 7
1D
b110000 F
b0 J
b101 K
b0 M
#805000
0%
05
0D
#810000
b110100 "
1%
b1 ,
b0 -
b101 .
b1100 /
15
b110100 7
1D
b110100 F
b1 J
b101 K
b1 M
#815000
0%
05
0D
#820000
b111000 "
1%
b0 ,
b1 -
b101 .
b1101 /
15
b111000 7
1D
b111000 F
b0 J
b101 K
b10 M
#825000
0%
05
0D
#830000
b111100 "
1%
b0xxxxxxxx ,
b0 -
b101 .
b1110 /
15
b111100 7
1D
b111100 F
b0xxxxxxxx J
b101 K
b11 M
#835000
0%
05
0D
#840000
b1000000 "
1%
b0 ,
b0xxxxxxxx -
b101 .
b1111 /
15
b1000000 7
1D
b1000000 F
b0 J
b101 K
b0 M
b1 N
#845000
0%
05
0D
#850000
b1000100 "
1%
b1 ,
b0 -
b101 .
b10000 /
15
b1000100 7
1D
b1000100 F
b1 J
b101 K
b1 M
#855000
0%
05
0D
#860000
b1001000 "
1%
b0 ,
b1 -
b101 .
b10001 /
15
b1001000 7
1D
b1001000 F
b0 J
b101 K
b10 M
#865000
0%
05
0D
#870000
b1001100 "
1%
b0xxxxxxxx ,
b0 -
b101 .
b10010 /
15
b1001100 7
1D
b1001100 F
b0xxxxxxxx J
b101 K
b11 M
#875000
0%
05
0D
#880000
b1010000 "
1%
b0 ,
b0xxxxxxxx -
b101 .
b10011 /
15
b1010000 7
1D
b1010000 F
b0 J
b101 K
b0 M
#885000
0%
05
0D
#890000
b1010100 "
1%
b1 ,
b0 -
b101 .
b10100 /
15
b1010100 7
1D
b1010100 F
b1 J
b101 K
b1 M
#895000
0%
05
0D
#900000
b1011000 "
1%
b0 ,
b1 -
b101 .
b10101 /
15
b1011000 7
1D
b1011000 F
b0 J
b101 K
b10 M
#905000
0%
05
0D
#910000
b1011100 "
1%
b0xxxxxxxx ,
b0 -
b101 .
b10110 /
15
b1011100 7
1D
b1011100 F
b0xxxxxxxx J
b101 K
b11 M
#915000
0%
05
0D
#920000
b1100000 "
1%
b0 ,
b0xxxxxxxx -
b101 .
b10111 /
15
b1100000 7
1D
b1100000 F
b0 J
b101 K
b0 M
#925000
0%
05
0D
#930000
b1100100 "
1%
b1 ,
b0 -
b101 .
b11000 /
15
b1100100 7
1D
b1100100 F
b1 J
b101 K
b1 M
#935000
0%
05
0D
#940000
b1101000 "
1%
b0 ,
b1 -
b101 .
b11001 /
15
b1101000 7
1D
b1101000 F
b0 J
b101 K
b10 M
#945000
0%
05
0D
#950000
b1101100 "
1%
b0xxxxxxxx ,
b0 -
b101 .
b11010 /
15
b1101100 7
1D
b1101100 F
b0xxxxxxxx J
b101 K
b11 M
#955000
0%
05
0D
#960000
b1110000 "
1%
b0 ,
b0xxxxxxxx -
b101 .
b11011 /
15
b1110000 7
1D
b1110000 F
b0 J
b101 K
b0 M
#965000
0%
05
0D
#970000
b1110100 "
1%
b1 ,
b0 -
b101 .
b11100 /
15
b1110100 7
1D
b1110100 F
b1 J
b101 K
b1 M
#975000
0%
05
0D
#980000
b1111000 "
1%
b0 ,
b1 -
b101 .
b11101 /
15
b1111000 7
1D
b1111000 F
b0 J
b101 K
b10 M
#985000
0%
05
0D
#990000
b1111100 "
1%
b0xxxxxxxx ,
b0 -
b101 .
b11110 /
15
b1111100 7
1D
b1111100 F
b0xxxxxxxx J
b101 K
b11 M
#995000
0%
05
0D
#1000000
b10000000 "
1%
b0 ,
b0xxxxxxxx -
b101 .
b11111 /
15
b10000000 7
1D
b10000000 F
b0 J
b101 K
b0 M
b10 N
