matbi/01_VerilogHDL/chapter_17_fsm_counter/dw_fsm_counter/dw_fsm_counter.v
`timescale 1ns/1ns

module dw_fsm_counter (
    input clk, 
    input reset_n,
    input i_run,
    input [6:0] i_num_cnt,
    output o_idle,
    output o_running,
    output o_done
);

reg [6:0] c_state;
wire is_done;
reg [6:0] num_cnt;
reg [6:0] cnt;

localparam S_IDLE = 2'b00;
localparam S_RUN = 2'b01;
localparam S_DONE = 2'b10;

//update c_state
always @(posedge clk or negedge reset_n) begin
    if (!reset_n)begin
        c_state <= 0;
    end
    else begin
        case(c_state)
            S_IDLE  : if(i_run) c_state <= S_RUN;
            S_RUN   : if(is_done) c_state <= S_DONE;
            S_DONE  : c_state <= S_IDLE;
        endcase    
    end
end


//compute max num
always @(posedge clk or negedge reset_n) begin
    if(!reset_n)begin
        num_cnt <= 0;
    end else if (o_running) begin
        num_cnt <= i_num_cnt;
    end else if (is_done) begin
        num_cnt <= 0;
    end
end

//compute count
always @(posedge clk or negedge reset_n) begin
    if(!reset_n)begin
        cnt <= 0;
    end else if (o_running) begin
        cnt <= cnt + 1;
    end else if (is_done) begin
        cnt <=0 ;
    end
    
end

assign o_idle       = (c_state == S_IDLE);
assign o_running    = (c_state == S_RUN);
assign o_done       = (c_state == S_DONE);


assign is_done = o_running && (cnt == num_cnt - 1);

endmodule

matbi/01_VerilogHDL/chapter_17_fsm_counter/dw_fsm_counter/dw_tb_fsm_counter.v
//////////////////////////////////////////////////////////////////////////////////
// Company: Personal
// Engineer: Matbi / Austin
//
// Create Date:
// Design Name: 
// Module Name: tb_fsm_counter_test
// Project Name:
// Target Devices:
// Tool Versions:
// Description: Verifify module fsm_counter_test
// Dependencies:
//
// Revision:
// Revision 0.01 - File Created
// Additional Comments:
//
//////////////////////////////////////////////////////////////////////////////////
`timescale 1ns / 1ps
module dw_tb_fsm_counter_test;
reg clk , reset_n;
reg 			i_run;
reg  [6:0]		i_num_cnt;
wire 			o_idle;
wire 			o_running;
wire 			o_done;
 
// clk gen
always
    #5 clk = ~clk;

initial begin
//initialize value
$dumpfile("output.vcd");
$dumpvars(0, dw_tb_fsm_counter_test);


$display("initialize value [%d]", $time);
    reset_n = 1;
    clk     = 0;
	i_run 	= 0;
	i_num_cnt = 0;
	
// reset_n gen
$display("Reset! [%d]", $time);
# 100
    reset_n = 0;
# 10
    reset_n = 1;
# 10
@(posedge clk);


$display("Check Idle [%d]", $time);
wait(o_idle);

$display("Start! [%d]", $time);
	i_num_cnt = 7'd100;
	i_run = 1;
@(posedge clk);
	i_run = 0;

$display("Wait Done [%d]", $time);
wait(o_done);

# 100
$display("Finish! [%d]", $time);
$finish;
end

// Call DUT
dw_fsm_counter u_dw_fsm_counter(
    .clk 			(clk),
    .reset_n 		(reset_n),
	.i_run 			(i_run),
	.i_num_cnt 		(i_num_cnt),
	.o_idle 		(o_idle),
	.o_running 		(o_running),
	.o_done 		(o_done)
    );
endmodule

matbi/01_VerilogHDL/chapter_17_fsm_counter/dw_fsm_counter/output.vcd
$date
	Fri Feb 26 14:31:24 2021
$end
$version
	Icarus Verilog
$end
$timescale
	1ps
$end
$scope module dw_tb_fsm_counter_test $end
$var wire 1 ! o_running $end
$var wire 1 " o_idle $end
$var wire 1 # o_done $end
$var reg 1 $ clk $end
$var reg 7 % i_num_cnt [6:0] $end
$var reg 1 & i_run $end
$var reg 1 ' reset_n $end
$scope module u_dw_fsm_counter $end
$var wire 1 $ clk $end
$var wire 7 ( i_num_cnt [6:0] $end
$var wire 1 & i_run $end
$var wire 1 ) is_done $end
$var wire 1 ' reset_n $end
$var wire 1 ! o_running $end
$var wire 1 " o_idle $end
$var wire 1 # o_done $end
$var reg 7 * c_state [6:0] $end
$var reg 7 + cnt [6:0] $end
$var reg 7 , num_cnt [6:0] $end
$upscope $end
$upscope $end
$enddefinitions $end
#0
$dumpvars
bx ,
bx +
bx *
x)
b0 (
1'
0&
b0 %
0$
x#
x"
x!
$end
#5000
1$
#10000
0$
#15000
1$
#20000
0$
#25000
1$
#30000
0$
#35000
1$
#40000
0$
#45000
1$
#50000
0$
#55000
1$
#60000
0$
#65000
1$
#70000
0$
#75000
1$
#80000
0$
#85000
1$
#90000
0$
#95000
1$
#100000
0)
1"
0!
0#
b0 *
b0 ,
b0 +
0$
0'
#105000
1$
#110000
0$
1'
#115000
1$
#120000
0$
#125000
0"
1!
b1 *
1&
b1100100 %
b1100100 (
1$
#130000
0$
#135000
b1100100 ,
b1 +
0&
1$
#140000
0$
#145000
b10 +
1$
#150000
0$
#155000
b11 +
1$
#160000
0$
#165000
b100 +
1$
#170000
0$
#175000
b101 +
1$
#180000
0$
#185000
b110 +
1$
#190000
0$
#195000
b111 +
1$
#200000
0$
#205000
b1000 +
1$
#210000
0$
#215000
b1001 +
1$
#220000
0$
#225000
b1010 +
1$
#230000
0$
#235000
b1011 +
1$
#240000
0$
#245000
b1100 +
1$
#250000
0$
#255000
b1101 +
1$
#260000
0$
#265000
b1110 +
1$
#270000
0$
#275000
b1111 +
1$
#280000
0$
#285000
b10000 +
1$
#290000
0$
#295000
b10001 +
1$
#300000
0$
#305000
b10010 +
1$
#310000
0$
#315000
b10011 +
1$
#320000
0$
#325000
b10100 +
1$
#330000
0$
#335000
b10101 +
1$
#340000
0$
#345000
b10110 +
1$
#350000
0$
#355000
b10111 +
1$
#360000
0$
#365000
b11000 +
1$
#370000
0$
#375000
b11001 +
1$
#380000
0$
#385000
b11010 +
1$
#390000
0$
#395000
b11011 +
1$
#400000
0$
#405000
b11100 +
1$
#410000
0$
#415000
b11101 +
1$
#420000
0$
#425000
b11110 +
1$
#430000
0$
#435000
b11111 +
1$
#440000
0$
#445000
b100000 +
1$
#450000
0$
#455000
b100001 +
1$
#460000
0$
#465000
b100010 +
1$
#470000
0$
#475000
b100011 +
1$
#480000
0$
#485000
b100100 +
1$
#490000
0$
#495000
b100101 +
1$
#500000
0$
#505000
b100110 +
1$
#510000
0$
#515000
b100111 +
1$
#520000
0$
#525000
b101000 +
1$
#530000
0$
#535000
b101001 +
1$
#540000
0$
#545000
b101010 +
1$
#550000
0$
#555000
b101011 +
1$
#560000
0$
#565000
b101100 +
1$
#570000
0$
#575000
b101101 +
1$
#580000
0$
#585000
b101110 +
1$
#590000
0$
#595000
b101111 +
1$
#600000
0$
#605000
b110000 +
1$
#610000
0$
#615000
b110001 +
1$
#620000
0$
#625000
b110010 +
1$
#630000
0$
#635000
b110011 +
1$
#640000
0$
#645000
b110100 +
1$
#650000
0$
#655000
b110101 +
1$
#660000
0$
#665000
b110110 +
1$
#670000
0$
#675000
b110111 +
1$
#680000
0$
#685000
b111000 +
1$
#690000
0$
#695000
b111001 +
1$
#700000
0$
#705000
b111010 +
1$
#710000
0$
#715000
b111011 +
1$
#720000
0$
#725000
b111100 +
1$
#730000
0$
#735000
b111101 +
1$
#740000
0$
#745000
b111110 +
1$
#750000
0$
#755000
b111111 +
1$
#760000
0$
#765000
b1000000 +
1$
#770000
0$
#775000
b1000001 +
1$
#780000
0$
#785000
b1000010 +
1$
#790000
0$
#795000
b1000011 +
1$
#800000
0$
#805000
b1000100 +
1$
#810000
0$
#815000
b1000101 +
1$
#820000
0$
#825000
b1000110 +
1$
#830000
0$
#835000
b1000111 +
1$
#840000
0$
#845000
b1001000 +
1$
#850000
0$
#855000
b1001001 +
1$
#860000
0$
#865000
b1001010 +
1$
#870000
0$
#875000
b1001011 +
1$
#880000
0$
#885000
b1001100 +
1$
#890000
0$
#895000
b1001101 +
1$
#900000
0$
#905000
b1001110 +
1$
#910000
0$
#915000
b1001111 +
1$
#920000
0$
#925000
b1010000 +
1$
#930000
0$
#935000
b1010001 +
1$
#940000
0$
#945000
b1010010 +
1$
#950000
0$
#955000
b1010011 +
1$
#960000
0$
#965000
b1010100 +
1$
#970000
0$
#975000
b1010101 +
1$
#980000
0$
#985000
b1010110 +
1$
#990000
0$
#995000
b1010111 +
1$
#1000000
0$
#1005000
b1011000 +
1$
#1010000
0$
#1015000
b1011001 +
1$
#1020000
0$
#1025000
b1011010 +
1$
#1030000
0$
#1035000
b1011011 +
1$
#1040000
0$
#1045000
b1011100 +
1$
#1050000
0$
#1055000
b1011101 +
1$
#1060000
0$
#1065000
b1011110 +
1$
#1070000
0$
#1075000
b1011111 +
1$
#1080000
0$
#1085000
b1100000 +
1$
#1090000
0$
#1095000
b1100001 +
1$
#1100000
0$
#1105000
b1100010 +
1$
#1110000
0$
#1115000
1)
b1100011 +
1$
#1120000
0$
#1125000
0)
b1100100 +
0!
1#
b10 *
1$
#1130000
0$
#1135000
1"
0#
b0 *
1$
