matbi/01_VerilogHDL/chapter_20/dongwon_cache.v
//Description: Direct mapped cache

module dongwon_cache
//param
#(
    parameter ADDR_WIDTH = 32,
    parameter DATA_WIDTH = 32,          //2^5
    parameter CACHE_SIZE = 4096,        //2^12
    parameter CACHE_MODE = "DIRECT MAPPED"
)
(
    input clk,
    input reset_n,
    input [ADDR_WIDTH-1:0] addr,
    input we,
    input run,
    input [DATA_WIDTH-1:0] in_data,
    output reg [DATA_WIDTH-1:0] out_data,
    output reg [2:0] state_of_cache
);

localparam SIZE_OF_BYTE_OFFSET = $clog2(DATA_WIDTH/8);
localparam SIZE_OF_INDEX = $clog2(CACHE_SIZE) - SIZE_OF_BYTE_OFFSET;
localparam SIZE_OF_VALID = 1;
localparam SIZE_OF_TAG = (ADDR_WIDTH)-(SIZE_OF_INDEX)-(SIZE_OF_BYTE_OFFSET);
localparam SIZE_OF_CACHE_LINE = (SIZE_OF_VALID)+(SIZE_OF_TAG)+(DATA_WIDTH);
localparam IDX_VALID = SIZE_OF_CACHE_LINE - 1; 

//Cache
reg [SIZE_OF_CACHE_LINE-1:0] cache_line[0:SIZE_OF_INDEX-1];

wire [SIZE_OF_BYTE_OFFSET-1:0] byte_offset;
wire [SIZE_OF_INDEX-1:0] index; 
wire [SIZE_OF_TAG-1:0] tag;

//Parsing address -> tag/index/byte offset
assign byte_offset = addr[SIZE_OF_BYTE_OFFSET-1 : 0];
assign index = addr[SIZE_OF_INDEX-1 : SIZE_OF_BYTE_OFFSET];
assign tag = addr[SIZE_OF_TAG-1 : SIZE_OF_INDEX+SIZE_OF_BYTE_OFFSET];


//Cache initialization
integer iter=0;
always @(posedge clk or negedge reset_n) begin
    if(!reset_n)begin
        for(iter=0; iter < CACHE_SIZE-1; iter=iter+1) begin
            cache_line[iter] <= {DATA_WIDTH{1'b0}};
        end       
    end
end

//update state of cache {Read|Write, Hit|Miss}
localparam CACHE_WRITE        = 3'b010;
localparam CACHE_READ_MISS    = 3'b100;
localparam CACHE_READ_HIT     = 3'b101;
localparam CACHE_IDLE         = 3'b000;

//localparam CACHE_WRITE_MISS   = 2'b10;
//localparam CACHE_WRITE_HIT    = 2'b11;

wire [3:0] abc;
assign abc = in_data & 32'hffff_ffff;

//Update Read & Write
always @(posedge clk) begin
    state_of_cache = CACHE_IDLE;
    if((CACHE_MODE == "DIRECT MAPPED") && run) begin
        if(we) begin                                            
                if(cache_line[index][IDX_VALID] == 0) begin  
                    state_of_cache <= CACHE_WRITE;
                    cache_line[index][DATA_WIDTH-1:0] <= in_data;
                    cache_line[index][IDX_VALID] <= 1'b1;
                end else                          
                    state_of_cache <= CACHE_WRITE;              
                    cache_line[index][DATA_WIDTH-1] <=  in_data;
                end
        else begin                                              
                if(cache_line[index][IDX_VALID] == 0) begin 
                    state_of_cache <= CACHE_READ_MISS;    
                    cache_line[index][DATA_WIDTH-1:0] <= in_data; //from RAM
                    cache_line[index][IDX_VALID] <= 1'b1;
                end else begin                                  
                    state_of_cache <= CACHE_READ_HIT;
                    out_data <= cache_line[index] & 32'hffff_ffff;
                    cache_line[index][IDX_VALID] <= 1'b1;
                end                                     
            end                 
        end
end  

endmodule

matbi/01_VerilogHDL/chapter_20/dongwon_ram.v
`timescale 1 ns/ 1 ps
module dongwon_ram
#(
    parameter ADDR_WIDTH = 8,
    parameter DATA_WIDTH = 8,
    parameter MEM_SIZE = 4096
)
(
    input clk,
    input reset_n,
    input [ADDR_WIDTH-1:0] addr,
    input [DATA_WIDTH-1:0] in_data,
    input run,
    input we,
    input [2:0] state_of_cache,
    output reg [DATA_WIDTH-1:0] out_data = 8'b0000_0000
);

localparam CACHE_WRITE        = 3'b010;
localparam CACHE_READ_MISS    = 3'b100;
localparam CACHE_READ_HIT     = 3'b101;
localparam CACHE_IDLE         = 3'b000;



//(* ram_style = "block" *)reg [DATA_WIDTH-1:0] ram[0:MEM_SIZE-1];
//reg [DATA_WIDTH-1:0] ram[0:MEM_SIZE-1];

reg [8-1:0] ram[0:MEM_SIZE-1];
integer iter=0;
always @(posedge clk or negedge reset_n) begin
    if(!reset_n)begin
        for(iter=0; iter<MEM_SIZE-1; iter=iter+1)begin
            ram[iter] <= {DATA_WIDTH{1'b0}};
        end
    end
end

// read & write
always @(posedge clk) begin
    if(run) begin
        if (we) begin
            ram[addr] <= (in_data)&(8'hff);
            ram[addr+1] <= (in_data>>8)&(8'hff);
            ram[addr+2] <= (in_data>>16)&(8'hff);
            ram[addr+3] <= (in_data>>24)&(8'hff);    
        end
            
        else if(~we)begin
            out_data <= (ram[addr+0]&(8'hff)<<0)
                        |(ram[addr+1]&(8'hff)<<8)
                        |(ram[addr+2]&(8'hff)<<16)
                        |(ram[addr+3]&(8'hff)<<24);        
        end
    end    
end

endmodule

matbi/01_VerilogHDL/chapter_20/tb_dongwon_ram.v
`timescale 1 ns/ 1 ps

`define ADDR_WIDTH 32
`define DATA_WIDTH 32
`define MEM_SIZE 1024
`define CACHE_SIZE 64
`define CACHE_MODE "DIRECT MAPPED"

module tb_dongwon_ram ();

//Program cnter
//wire [`ADDR_WIDTH-1:0] pc;
reg pc_restart;
reg [`ADDR_WIDTH-1:0] pc;
//Memory
reg r_we;
reg c_we;
reg clk;
reg reset_n;
reg r_run;
reg c_run;

reg [`DATA_WIDTH-1:0] r_in_data;
reg [`DATA_WIDTH-1:0] c_in_data;
wire [`DATA_WIDTH-1:0] r_out_data;
wire [`DATA_WIDTH-1:0] c_out_data;
reg [`DATA_WIDTH-1:0] t_out_data;
wire [2:0] state_of_cache;

//local praram
localparam CACHE_WRITE        = 3'b010;
localparam CACHE_READ_MISS    = 3'b100;
localparam CACHE_READ_HIT     = 3'b101;
localparam CACHE_IDLE         = 3'b000;

integer iter = 0;
integer count = 1;
//clock generation
always
    #5 clk = ~clk;

initial begin
    $dumpfile("output.vcd");
    $dumpvars(0, tb_dongwon_ram);

    //initialization
    reset_n = 1;
    pc_restart = 1;
    clk = 1; 
    
    r_run = 1;
    r_we = 0;
    c_run = 0;
    c_we = 0;
    
    c_in_data = 0;
    r_in_data = 0;

    //1. RAM initialization (OK) 
    begin
        #10
        reset_n <= 0 ;     
        r_we <= 1; 
        r_run <=1;
        pc = 0;

        #10
        reset_n = 1;
        for (iter=0; iter<32; iter=iter+1) begin
            r_in_data <= iter;
            pc <= pc+4;
            #10;
        end
    end
    
    // 2. Cache read(Cache miss) 
    begin
        pc_restart <= 0;
        r_run <=1;
        c_run <=1;
        r_we <= 0; 
        c_we <= 0;
        pc = 0;

        #10
        pc_restart <= 1;
        for (iter=0; iter<32; iter=iter+1) begin
                c_in_data <= r_out_data;
                pc = pc+4;
                #10;
        end
    end
    

    // 3. Cache read(Cache hit)
    begin
        #10
        c_we <= 0;
        r_run <=0;
        c_run <=1;
        pc_restart <= 0;
        pc = 0;

        #10
        pc_restart <= 1;
        for (iter=0; iter<32; iter=iter+1) begin     
            if(state_of_cache == CACHE_READ_HIT)
                t_out_data <= c_out_data;
                pc <= pc+4;
                #10;
        end
    end
    

    $finish;
end


// Memory
dongwon_ram 
#(  
    .ADDR_WIDTH             (`ADDR_WIDTH),
    .DATA_WIDTH             (`DATA_WIDTH),
    .MEM_SIZE               (`MEM_SIZE)
)
u_dongwon_ram (
    .clk                    (clk),
    .reset_n                (reset_n),
    .addr                   (pc),
    .run                    (r_run),
    .in_data                (r_in_data),
    .we                     (r_we),
    .out_data               (r_out_data),
    .state_of_cache         (state_of_cache)
);


//cpu
// dongwon_cpu
// #(
//     .ADDR_WIDTH             (`ADDR_WIDTH)
// )
// u_dongwon_cpu
// (
//     .reset_n                (reset_n),
//     .clk                    (clk),
//     .pc                     (pc),
//     .restart_n              (pc_restart)
// );

//cache
dongwon_cache
#(
    .ADDR_WIDTH             (`ADDR_WIDTH),
    .DATA_WIDTH             (`DATA_WIDTH),
    .CACHE_SIZE             (`CACHE_SIZE),
    .CACHE_MODE             (`CACHE_MODE)
)       
u_dongwon_cache(        
    .clk                    (clk),
    .reset_n                (reset_n),
    .we                     (c_we),
    .addr                   (pc),
    .run                    (c_run),
    .out_data               (c_out_data),
    .in_data                (c_in_data),
    .state_of_cache         (state_of_cache)
);
    
endmodule

matbi/01_VerilogHDL/chapter_20/output.vcd
$date
	Tue Feb 23 16:00:31 2021
$end
$version
	Icarus Verilog
$end
$timescale
	1ps
$end
$scope module tb_dongwon_ram $end
$var wire 3 ! state_of_cache [2:0] $end
$var wire 32 " r_out_data [31:0] $end
$var wire 32 # c_out_data [31:0] $end
$var reg 32 $ c_in_data [31:0] $end
$var reg 1 % c_run $end
$var reg 1 & c_we $end
$var reg 1 ' clk $end
$var reg 32 ( pc [31:0] $end
$var reg 1 ) pc_restart $end
$var reg 32 * r_in_data [31:0] $end
$var reg 1 + r_run $end
$var reg 1 , r_we $end
$var reg 1 - reset_n $end
$var reg 32 . t_out_data [31:0] $end
$var integer 32 / count [31:0] $end
$var integer 32 0 iter [31:0] $end
$scope module u_dongwon_cache $end
$var wire 32 1 addr [31:0] $end
$var wire 1 ' clk $end
$var wire 32 2 in_data [31:0] $end
$var wire 1 - reset_n $end
$var wire 1 % run $end
$var wire 1 & we $end
$var wire 25 3 tag [24:0] $end
$var wire 5 4 index [4:0] $end
$var wire 2 5 byte_offset [1:0] $end
$var wire 4 6 abc [3:0] $end
$var reg 32 7 out_data [31:0] $end
$var reg 3 8 state_of_cache [2:0] $end
$var integer 32 9 iter [31:0] $end
$upscope $end
$scope module u_dongwon_ram $end
$var wire 32 : addr [31:0] $end
$var wire 1 ' clk $end
$var wire 32 ; in_data [31:0] $end
$var wire 1 - reset_n $end
$var wire 1 + run $end
$var wire 3 < state_of_cache [2:0] $end
$var wire 1 , we $end
$var reg 32 = out_data [31:0] $end
$var integer 32 > iter [31:0] $end
$upscope $end
$upscope $end
$enddefinitions $end
#0
$dumpvars
b0 >
b0xxxxxxxx =
b0 <
b0 ;
bx :
b0 9
b0 8
bx 7
b0 6
bx 5
b0xxx 4
b0xxxxxxxxxxxxxxxxxx 3
b0 2
bx 1
b0 0
b1 /
bx .
1-
0,
1+
b0 *
1)
bx (
1'
0&
0%
b0 $
bx #
b0xxxxxxxx "
b0 !
$end
#5000
0'
#10000
b1111111111 >
b1111111 9
1,
0-
b0 5
b0 4
b0 3
1'
b0 (
b0 1
b0 :
#15000
0'
#20000
b1 4
b100 (
b100 1
b100 :
1'
1-
#25000
0'
#30000
b10 4
b1000 (
b1000 1
b1000 :
b1 *
b1 ;
1'
b1 0
#35000
0'
#40000
b11 4
b1100 (
b1100 1
b1100 :
b10 *
b10 ;
1'
b10 0
#45000
0'
#50000
b100 4
b10000 (
b10000 1
b10000 :
b11 *
b11 ;
1'
b11 0
#55000
0'
#60000
b101 4
b10100 (
b10100 1
b10100 :
b100 *
b100 ;
1'
b100 0
#65000
0'
#70000
b110 4
b11000 (
b11000 1
b11000 :
b101 *
b101 ;
1'
b101 0
#75000
0'
#80000
b111 4
b11100 (
b11100 1
b11100 :
b110 *
b110 ;
1'
b110 0
#85000
0'
#90000
b0 4
b100000 (
b100000 1
b100000 :
b111 *
b111 ;
1'
b111 0
#95000
0'
#100000
b1 4
b100100 (
b100100 1
b100100 :
b1000 *
b1000 ;
1'
b1000 0
#105000
0'
#110000
b10 4
b101000 (
b101000 1
b101000 :
b1001 *
b1001 ;
1'
b1001 0
#115000
0'
#120000
b11 4
b101100 (
b101100 1
b101100 :
b1010 *
b1010 ;
1'
b1010 0
#125000
0'
#130000
b100 4
b110000 (
b110000 1
b110000 :
b1011 *
b1011 ;
1'
b1011 0
#135000
0'
#140000
b101 4
b110100 (
b110100 1
b110100 :
b1100 *
b1100 ;
1'
b1100 0
#145000
0'
#150000
b110 4
b111000 (
b111000 1
b111000 :
b1101 *
b1101 ;
1'
b1101 0
#155000
0'
#160000
b111 4
b111100 (
b111100 1
b111100 :
b1110 *
b1110 ;
1'
b1110 0
#165000
0'
#170000
b0 4
b1000000 (
b1000000 1
b1000000 :
b1111 *
b1111 ;
1'
b1111 0
#175000
0'
#180000
b1 4
b1000100 (
b1000100 1
b1000100 :
b10000 *
b10000 ;
1'
b10000 0
#185000
0'
#190000
b10 4
b1001000 (
b1001000 1
b1001000 :
b10001 *
b10001 ;
1'
b10001 0
#195000
0'
#200000
b11 4
b1001100 (
b1001100 1
b1001100 :
b10010 *
b10010 ;
1'
b10010 0
#205000
0'
#210000
b100 4
b1010000 (
b1010000 1
b1010000 :
b10011 *
b10011 ;
1'
b10011 0
#215000
0'
#220000
b101 4
b1010100 (
b1010100 1
b1010100 :
b10100 *
b10100 ;
1'
b10100 0
#225000
0'
#230000
b110 4
b1011000 (
b1011000 1
b1011000 :
b10101 *
b10101 ;
1'
b10101 0
#235000
0'
#240000
b111 4
b1011100 (
b1011100 1
b1011100 :
b10110 *
b10110 ;
1'
b10110 0
#245000
0'
#250000
b0 4
b1100000 (
b1100000 1
b1100000 :
b10111 *
b10111 ;
1'
b10111 0
#255000
0'
#260000
b1 4
b1100100 (
b1100100 1
b1100100 :
b11000 *
b11000 ;
1'
b11000 0
#265000
0'
#270000
b10 4
b1101000 (
b1101000 1
b1101000 :
b11001 *
b11001 ;
1'
b11001 0
#275000
0'
#280000
b11 4
b1101100 (
b1101100 1
b1101100 :
b11010 *
b11010 ;
1'
b11010 0
#285000
0'
#290000
b100 4
b1110000 (
b1110000 1
b1110000 :
b11011 *
b11011 ;
1'
b11011 0
#295000
0'
#300000
b101 4
b1110100 (
b1110100 1
b1110100 :
b11100 *
b11100 ;
1'
b11100 0
#305000
0'
#310000
b110 4
b1111000 (
b1111000 1
b1111000 :
b11101 *
b11101 ;
1'
b11101 0
#315000
0'
#320000
b111 4
b1111100 (
b1111100 1
b1111100 :
b11110 *
b11110 ;
1'
b11110 0
#325000
0'
#330000
b0 4
b1 3
b10000000 (
b10000000 1
b10000000 :
b11111 *
b11111 ;
1'
b11111 0
#335000
0'
#340000
0,
1%
0)
b0 3
1'
b0 (
b0 1
b0 :
b100000 0
#345000
0'
#350000
bx 6
b100 !
b100 8
b100 <
b0 "
b0 =
b0xxxxxxxx $
b0xxxxxxxx 2
1)
b1 4
1'
b100 (
b100 1
b100 :
b0 0
#355000
0'
#360000
b0 6
b1 "
b1 =
b0 $
b0 2
b100 !
b100 8
b100 <
b10 4
1'
b1000 (
b1000 1
b1000 :
b1 0
#365000
0'
#370000
b1 6
b10 "
b10 =
b1 $
b1 2
b100 !
b100 8
b100 <
b11 4
1'
b1100 (
b1100 1
b1100 :
b10 0
#375000
0'
#380000
b10 6
b11 "
b11 =
b10 $
b10 2
b100 !
b100 8
b100 <
b100 4
1'
b10000 (
b10000 1
b10000 :
b11 0
#385000
0'
#390000
b11 6
b100 "
b100 =
b11 $
b11 2
b101 !
b101 8
b101 <
b101 4
1'
b10100 (
b10100 1
b10100 :
b100 0
#395000
0'
#400000
b100 6
b101 "
b101 =
b100 $
b100 2
b101 !
b101 8
b101 <
b110 4
1'
b11000 (
b11000 1
b11000 :
b101 0
#405000
0'
#410000
b101 6
b110 "
b110 =
b101 $
b101 2
b101 !
b101 8
b101 <
b111 4
1'
b11100 (
b11100 1
b11100 :
b110 0
#415000
0'
#420000
b110 6
b111 "
b111 =
b110 $
b110 2
b100 !
b100 8
b100 <
b0 4
1'
b100000 (
b100000 1
b100000 :
b111 0
#425000
0'
#430000
b111 6
b0 #
b0 7
b1000 "
b1000 =
b111 $
b111 2
b101 !
b101 8
b101 <
b1 4
1'
b100100 (
b100100 1
b100100 :
b1000 0
#435000
0'
#440000
b1000 6
b1001 "
b1001 =
b0xxxxxxxx #
b0xxxxxxxx 7
b1000 $
b1000 2
b101 !
b101 8
b101 <
b10 4
1'
b101000 (
b101000 1
b101000 :
b1001 0
#445000
0'
#450000
b1001 6
b0 #
b0 7
b1010 "
b1010 =
b1001 $
b1001 2
b101 !
b101 8
b101 <
b11 4
1'
b101100 (
b101100 1
b101100 :
b1010 0
#455000
0'
#460000
b1010 6
b1011 "
b1011 =
b1 #
b1 7
b1010 $
b1010 2
b101 !
b101 8
b101 <
b100 4
1'
b110000 (
b110000 1
b110000 :
b1011 0
#465000
0'
#470000
b1011 6
bx #
bx 7
b1100 "
b1100 =
b1011 $
b1011 2
b101 !
b101 8
b101 <
b101 4
1'
b110100 (
b110100 1
b110100 :
b1100 0
#475000
0'
#480000
b1100 6
b1101 "
b1101 =
b1100 $
b1100 2
b101 !
b101 8
b101 <
b110 4
1'
b111000 (
b111000 1
b111000 :
b1101 0
#485000
0'
#490000
b1101 6
b1110 "
b1110 =
b1101 $
b1101 2
b101 !
b101 8
b101 <
b111 4
1'
b111100 (
b111100 1
b111100 :
b1110 0
#495000
0'
#500000
b1110 6
b1111 "
b1111 =
b101 #
b101 7
b1110 $
b1110 2
b101 !
b101 8
b101 <
b0 4
1'
b1000000 (
b1000000 1
b1000000 :
b1111 0
#505000
0'
#510000
b1111 6
b0 #
b0 7
b10000 "
b10000 =
b1111 $
b1111 2
b101 !
b101 8
b101 <
b1 4
1'
b1000100 (
b1000100 1
b1000100 :
b10000 0
#515000
0'
#520000
b0 6
b10001 "
b10001 =
b0xxxxxxxx #
b0xxxxxxxx 7
b10000 $
b10000 2
b101 !
b101 8
b101 <
b10 4
1'
b1001000 (
b1001000 1
b1001000 :
b10001 0
#525000
0'
#530000
b1 6
b0 #
b0 7
b10010 "
b10010 =
b10001 $
b10001 2
b101 !
b101 8
b101 <
b11 4
1'
b1001100 (
b1001100 1
b1001100 :
b10010 0
#535000
0'
#540000
b10 6
b10011 "
b10011 =
b1 #
b1 7
b10010 $
b10010 2
b101 !
b101 8
b101 <
b100 4
1'
b1010000 (
b1010000 1
b1010000 :
b10011 0
#545000
0'
#550000
b11 6
bx #
bx 7
b10100 "
b10100 =
b10011 $
b10011 2
b101 !
b101 8
b101 <
b101 4
1'
b1010100 (
b1010100 1
b1010100 :
b10100 0
#555000
0'
#560000
b100 6
b10101 "
b10101 =
b10100 $
b10100 2
b101 !
b101 8
b101 <
b110 4
1'
b1011000 (
b1011000 1
b1011000 :
b10101 0
#565000
0'
#570000
b101 6
b10110 "
b10110 =
b10101 $
b10101 2
b101 !
b101 8
b101 <
b111 4
1'
b1011100 (
b1011100 1
b1011100 :
b10110 0
#575000
0'
#580000
b110 6
b10111 "
b10111 =
b101 #
b101 7
b10110 $
b10110 2
b101 !
b101 8
b101 <
b0 4
1'
b1100000 (
b1100000 1
b1100000 :
b10111 0
#585000
0'
#590000
b111 6
b0 #
b0 7
b11000 "
b11000 =
b10111 $
b10111 2
b101 !
b101 8
b101 <
b1 4
1'
b1100100 (
b1100100 1
b1100100 :
b11000 0
#595000
0'
#600000
b1000 6
b11001 "
b11001 =
b0xxxxxxxx #
b0xxxxxxxx 7
b11000 $
b11000 2
b101 !
b101 8
b101 <
b10 4
1'
b1101000 (
b1101000 1
b1101000 :
b11001 0
#605000
0'
#610000
b1001 6
b0 #
b0 7
b11010 "
b11010 =
b11001 $
b11001 2
b101 !
b101 8
b101 <
b11 4
1'
b1101100 (
b1101100 1
b1101100 :
b11010 0
#615000
0'
#620000
b1010 6
b11011 "
b11011 =
b1 #
b1 7
b11010 $
b11010 2
b101 !
b101 8
b101 <
b100 4
1'
b1110000 (
b1110000 1
b1110000 :
b11011 0
#625000
0'
#630000
b1011 6
bx #
bx 7
b11100 "
b11100 =
b11011 $
b11011 2
b101 !
b101 8
b101 <
b101 4
1'
b1110100 (
b1110100 1
b1110100 :
b11100 0
#635000
0'
#640000
b1100 6
b11101 "
b11101 =
b11100 $
b11100 2
b101 !
b101 8
b101 <
b110 4
1'
b1111000 (
b1111000 1
b1111000 :
b11101 0
#645000
0'
#650000
b1101 6
b11110 "
b11110 =
b11101 $
b11101 2
b101 !
b101 8
b101 <
b111 4
1'
b1111100 (
b1111100 1
b1111100 :
b11110 0
#655000
0'
#660000
b1110 6
b0 "
b0 =
b101 #
b101 7
b11110 $
b11110 2
b101 !
b101 8
b101 <
b0 4
b1 3
1'
b10000000 (
b10000000 1
b10000000 :
b11111 0
#665000
0'
#670000
b0 6
b0 #
b0 7
b0 $
b0 2
b101 !
b101 8
b101 <
b1 4
1'
b10000100 (
b10000100 1
b10000100 :
b100000 0
#675000
0'
#680000
b0xxxxxxxx #
b0xxxxxxxx 7
b101 !
b101 8
b101 <
b10 4
1'
b10001000 (
b10001000 1
b10001000 :
b100001 0
#685000
0'
#690000
b0 #
b0 7
b101 !
b101 8
b101 <
b11 4
1'
b10001100 (
b10001100 1
b10001100 :
b100010 0
#695000
0'
#700000
b1 #
b1 7
b101 !
b101 8
b101 <
b100 4
1'
b10010000 (
b10010000 1
b10010000 :
b100011 0
#705000
0'
#710000
bx #
bx 7
b101 !
b101 8
b101 <
b101 4
1'
b10010100 (
b10010100 1
b10010100 :
b100100 0
#715000
0'
#720000
b101 !
b101 8
b101 <
b110 4
1'
b10011000 (
b10011000 1
b10011000 :
b100101 0
#725000
0'
#730000
b101 !
b101 8
b101 <
b111 4
1'
b10011100 (
b10011100 1
b10011100 :
b100110 0
#735000
0'
#740000
b101 #
b101 7
b101 !
b101 8
b101 <
b0 4
1'
b10100000 (
b10100000 1
b10100000 :
b100111 0
#745000
0'
#750000
b0 #
b0 7
b101 !
b101 8
b101 <
b1 4
1'
b10100100 (
b10100100 1
b10100100 :
b101000 0
#755000
0'
#760000
b0xxxxxxxx #
b0xxxxxxxx 7
b101 !
b101 8
b101 <
b10 4
1'
b10101000 (
b10101000 1
b10101000 :
b101001 0
#765000
0'
#770000
b0 #
b0 7
b101 !
b101 8
b101 <
b11 4
1'
b10101100 (
b10101100 1
b10101100 :
b101010 0
#775000
0'
#780000
b1 #
b1 7
b101 !
b101 8
b101 <
b100 4
1'
b10110000 (
b10110000 1
b10110000 :
b101011 0
#785000
0'
#790000
bx #
bx 7
b101 !
b101 8
b101 <
b101 4
1'
b10110100 (
b10110100 1
b10110100 :
b101100 0
#795000
0'
#800000
b101 !
b101 8
b101 <
b110 4
1'
b10111000 (
b10111000 1
b10111000 :
b101101 0
#805000
0'
#810000
b101 !
b101 8
b101 <
b111 4
1'
b10111100 (
b10111100 1
b10111100 :
b101110 0
#815000
0'
#820000
b101 #
b101 7
b101 !
b101 8
b101 <
b0 4
1'
b11000000 (
b11000000 1
b11000000 :
b101111 0
#825000
0'
#830000
b0 #
b0 7
b101 !
b101 8
b101 <
b1 4
1'
b11000100 (
b11000100 1
b11000100 :
b110000 0
#835000
0'
#840000
b0xxxxxxxx #
b0xxxxxxxx 7
b101 !
b101 8
b101 <
b10 4
1'
b11001000 (
b11001000 1
b11001000 :
b110001 0
#845000
0'
#850000
b0 #
b0 7
b101 !
b101 8
b101 <
b11 4
1'
b11001100 (
b11001100 1
b11001100 :
b110010 0
#855000
0'
#860000
b1 #
b1 7
b101 !
b101 8
b101 <
b100 4
1'
b11010000 (
b11010000 1
b11010000 :
b110011 0
#865000
0'
#870000
bx #
bx 7
b101 !
b101 8
b101 <
b101 4
1'
b11010100 (
b11010100 1
b11010100 :
b110100 0
#875000
0'
#880000
b101 !
b101 8
b101 <
b110 4
1'
b11011000 (
b11011000 1
b11011000 :
b110101 0
#885000
0'
#890000
b101 !
b101 8
b101 <
b111 4
1'
b11011100 (
b11011100 1
b11011100 :
b110110 0
#895000
0'
#900000
b101 #
b101 7
b101 !
b101 8
b101 <
b0 4
1'
b11100000 (
b11100000 1
b11100000 :
b110111 0
#905000
0'
#910000
b0 #
b0 7
b101 !
b101 8
b101 <
b1 4
1'
b11100100 (
b11100100 1
b11100100 :
b111000 0
#915000
0'
#920000
b0xxxxxxxx #
b0xxxxxxxx 7
b101 !
b101 8
b101 <
b10 4
1'
b11101000 (
b11101000 1
b11101000 :
b111001 0
#925000
0'
#930000
b0 #
b0 7
b101 !
b101 8
b101 <
b11 4
1'
b11101100 (
b11101100 1
b11101100 :
b111010 0
#935000
0'
#940000
b1 #
b1 7
b101 !
b101 8
b101 <
b100 4
1'
b11110000 (
b11110000 1
b11110000 :
b111011 0
#945000
0'
#950000
bx #
bx 7
b101 !
b101 8
b101 <
b101 4
1'
b11110100 (
b11110100 1
b11110100 :
b111100 0
#955000
0'
#960000
b101 !
b101 8
b101 <
b110 4
1'
b11111000 (
b11111000 1
b11111000 :
b111101 0
#965000
0'
#970000
b101 !
b101 8
b101 <
b111 4
1'
b11111100 (
b11111100 1
b11111100 :
b111110 0
#975000
0'
#980000
b101 #
b101 7
b101 !
b101 8
b101 <
b0 4
b10 3
1'
b100000000 (
b100000000 1
b100000000 :
b111111 0
#985000
0'
#990000
b101 !
b101 8
b101 <
1'
b1000000 0
#995000
0'
#1000000
b11111 "
b11111 =
0)
0+
b101 !
b101 8
b101 <
b0 3
1'
b0 (
b0 1
b0 :
#1005000
0'
#1010000
b1 4
b100 (
b100 1
b100 :
b101 .
1)
b101 !
b101 8
b101 <
1'
b0 0
#1015000
0'
#1020000
b10 4
b0 #
b0 7
b1000 (
b1000 1
b1000 :
b101 !
b101 8
b101 <
1'
b1 0
#1025000
0'
#1030000
b11 4
b0xxxxxxxx #
b0xxxxxxxx 7
b1100 (
b1100 1
b1100 :
b0 .
b101 !
b101 8
b101 <
1'
b10 0
#1035000
0'
#1040000
b100 4
b0 #
b0 7
b10000 (
b10000 1
b10000 :
b0xxxxxxxx .
b101 !
b101 8
b101 <
1'
b11 0
#1045000
0'
#1050000
b101 4
b1 #
b1 7
b10100 (
b10100 1
b10100 :
b0 .
b101 !
b101 8
b101 <
1'
b100 0
#1055000
0'
#1060000
b110 4
bx #
bx 7
b11000 (
b11000 1
b11000 :
b1 .
b101 !
b101 8
b101 <
1'
b101 0
#1065000
0'
#1070000
b111 4
b11100 (
b11100 1
b11100 :
bx .
b101 !
b101 8
b101 <
1'
b110 0
#1075000
0'
#1080000
b0 4
b100000 (
b100000 1
b100000 :
b101 !
b101 8
b101 <
1'
b111 0
#1085000
0'
#1090000
b1 4
b101 #
b101 7
b100100 (
b100100 1
b100100 :
b101 !
b101 8
b101 <
1'
b1000 0
#1095000
0'
#1100000
b10 4
b0 #
b0 7
b101000 (
b101000 1
b101000 :
b101 .
b101 !
b101 8
b101 <
1'
b1001 0
#1105000
0'
#1110000
b11 4
b0xxxxxxxx #
b0xxxxxxxx 7
b101100 (
b101100 1
b101100 :
b0 .
b101 !
b101 8
b101 <
1'
b1010 0
#1115000
0'
#1120000
b100 4
b0 #
b0 7
b110000 (
b110000 1
b110000 :
b0xxxxxxxx .
b101 !
b101 8
b101 <
1'
b1011 0
#1125000
0'
#1130000
b101 4
b1 #
b1 7
b110100 (
b110100 1
b110100 :
b0 .
b101 !
b101 8
b101 <
1'
b1100 0
#1135000
0'
#1140000
b110 4
bx #
bx 7
b111000 (
b111000 1
b111000 :
b1 .
b101 !
b101 8
b101 <
1'
b1101 0
#1145000
0'
#1150000
b111 4
b111100 (
b111100 1
b111100 :
bx .
b101 !
b101 8
b101 <
1'
b1110 0
#1155000
0'
#1160000
b0 4
b1000000 (
b1000000 1
b1000000 :
b101 !
b101 8
b101 <
1'
b1111 0
#1165000
0'
#1170000
b1 4
b101 #
b101 7
b1000100 (
b1000100 1
b1000100 :
b101 !
b101 8
b101 <
1'
b10000 0
#1175000
0'
#1180000
b10 4
b0 #
b0 7
b1001000 (
b1001000 1
b1001000 :
b101 .
b101 !
b101 8
b101 <
1'
b10001 0
#1185000
0'
#1190000
b11 4
b0xxxxxxxx #
b0xxxxxxxx 7
b1001100 (
b1001100 1
b1001100 :
b0 .
b101 !
b101 8
b101 <
1'
b10010 0
#1195000
0'
#1200000
b100 4
b0 #
b0 7
b1010000 (
b1010000 1
b1010000 :
b0xxxxxxxx .
b101 !
b101 8
b101 <
1'
b10011 0
#1205000
0'
#1210000
b101 4
b1 #
b1 7
b1010100 (
b1010100 1
b1010100 :
b0 .
b101 !
b101 8
b101 <
1'
b10100 0
#1215000
0'
#1220000
b110 4
bx #
bx 7
b1011000 (
b1011000 1
b1011000 :
b1 .
b101 !
b101 8
b101 <
1'
b10101 0
#1225000
0'
#1230000
b111 4
b1011100 (
b1011100 1
b1011100 :
bx .
b101 !
b101 8
b101 <
1'
b10110 0
#1235000
0'
#1240000
b0 4
b1100000 (
b1100000 1
b1100000 :
b101 !
b101 8
b101 <
1'
b10111 0
#1245000
0'
#1250000
b1 4
b101 #
b101 7
b1100100 (
b1100100 1
b1100100 :
b101 !
b101 8
b101 <
1'
b11000 0
#1255000
0'
#1260000
b10 4
b0 #
b0 7
b1101000 (
b1101000 1
b1101000 :
b101 .
b101 !
b101 8
b101 <
1'
b11001 0
#1265000
0'
#1270000
b11 4
b0xxxxxxxx #
b0xxxxxxxx 7
b1101100 (
b1101100 1
b1101100 :
b0 .
b101 !
b101 8
b101 <
1'
b11010 0
#1275000
0'
#1280000
b100 4
b0 #
b0 7
b1110000 (
b1110000 1
b1110000 :
b0xxxxxxxx .
b101 !
b101 8
b101 <
1'
b11011 0
#1285000
0'
#1290000
b101 4
b1 #
b1 7
b1110100 (
b1110100 1
b1110100 :
b0 .
b101 !
b101 8
b101 <
1'
b11100 0
#1295000
0'
#1300000
b110 4
bx #
bx 7
b1111000 (
b1111000 1
b1111000 :
b1 .
b101 !
b101 8
b101 <
1'
b11101 0
#1305000
0'
#1310000
b111 4
b1111100 (
b1111100 1
b1111100 :
bx .
b101 !
b101 8
b101 <
1'
b11110 0
#1315000
0'
#1320000
b0 4
b1 3
b10000000 (
b10000000 1
b10000000 :
b101 !
b101 8
b101 <
1'
b11111 0
#1325000
0'
#1330000
b101 #
b101 7
b101 !
b101 8
b101 <
1'
b100000 0
